coreason_budget/__init__.py
coreason_budget/config.py
coreason_budget/exceptions.py
coreason_budget/guard.py
coreason_budget/ledger.py
coreason_budget/manager.py
coreason_budget/pricing.py
coreason_budget/utils/__init__.py
coreason_budget/utils/logger.py
coreason_budget/validation.py
coreason_budget-0.2.0.dist-info/METADATA
coreason_budget-0.2.0.dist-info/WHEEL
coreason_budget-0.2.0.dist-info/licenses/LICENSE
coreason_budget-0.2.0.dist-info/licenses/NOTICE
coreason_budget-0.2.0.dist-info/RECORD
