Metadata-Version: 2.4
Name: coreason_budget
Version: 0.2.0
Summary: enforces budget
License: # The Prosperity Public License 3.0.0
License-File: LICENSE
License-File: NOTICE
Author: Gowtham A Rao
Author-email: gowtham.rao@coreason.ai
Requires-Python: >=3.11
Classifier: License :: Other/Proprietary License
Classifier: Programming Language :: Python :: 3.12
Classifier: Operating System :: OS Independent
Requires-Dist: litellm (>=1.80.11,<2.0.0)
Requires-Dist: loguru (>=0.7.2,<0.8.0)
Requires-Dist: pydantic (>=2.0)
Requires-Dist: pydantic-settings (>=2.12.0,<3.0.0)
Requires-Dist: redis (>=7.1.0,<8.0.0)
Project-URL: Documentation, https://github.com/CoReason-AI/coreason_budget
Project-URL: Homepage, https://github.com/CoReason-AI/coreason_budget
Project-URL: Repository, https://github.com/CoReason-AI/coreason_budget
